<?xml version="1.0" encoding="utf-8"?>
<Dependencies>
  <ProductDependencies>
  </ProductDependencies>
  <ToolsetDependencies>
    <Dependency Name="Microsoft.DotNet.Arcade.Sdk" Version="11.0.0-beta.25524.1">
      <Uri>https://github.com/dotnet/arcade</Uri>
      <Sha>904bfd153de2a88471c00a7cdd3450948e758db8</Sha>
    </Dependency>
    <Dependency Name="Microsoft.DotNet.Build.Tasks.Packaging" Version="11.0.0-beta.25524.1">
      <Uri>https://github.com/dotnet/arcade</Uri>
      <Sha>904bfd153de2a88471c00a7cdd3450948e758db8</Sha>
    </Dependency>
  </ToolsetDependencies>
</Dependencies>
